spring_config_client/__init__.py
spring_config_client/client.py
spring_config_client_python-0.1.3.dist-info/METADATA
spring_config_client_python-0.1.3.dist-info/WHEEL
spring_config_client_python-0.1.3.dist-info/licenses/LICENSE
spring_config_client_python-0.1.3.dist-info/RECORD
