Metadata-Version: 2.4
Name: spring-config-client-python
Version: 0.1.3
Summary: Lightweight Spring Cloud Config client for Python
Project-URL: Homepage, https://github.com/tcivie/spring-config-client-python
Project-URL: Issues, https://github.com/tcivie/spring-config-client-python/issues
Author-email: Gleb Tcivie <gleb@tcivie.com>
License-Expression: MIT
License-File: LICENSE
Classifier: License :: OSI Approved :: MIT License
Classifier: Operating System :: OS Independent
Classifier: Programming Language :: Python :: 3
Classifier: Programming Language :: Python :: 3.9
Classifier: Programming Language :: Python :: 3.10
Classifier: Programming Language :: Python :: 3.11
Classifier: Programming Language :: Python :: 3.12
Requires-Python: >=3.9
Requires-Dist: requests>=2.31.0
Provides-Extra: dev
Requires-Dist: pytest-cov>=4.1.0; extra == 'dev'
Requires-Dist: pytest>=7.4.0; extra == 'dev'
